drawioedit/N2G_DrawIO.py
drawioedit/__init__.py
drawioedit-0.3.6.dist-info/LICENSE
drawioedit-0.3.6.dist-info/METADATA
drawioedit-0.3.6.dist-info/WHEEL
drawioedit-0.3.6.dist-info/top_level.txt
drawioedit-0.3.6.dist-info/RECORD
