Metadata-Version: 2.1
Name: drawioedit
Version: 0.3.6
Summary: Simple interface to edit drawio files
Home-page: https://github.com/jinjamator/drawioedit
Author: Wilhelm Putz
Author-email: wp@aci.guru
License: ASL V2
Platform: UNKNOWN
Classifier: License :: OSI Approved :: Apache Software License
Classifier: Programming Language :: Python :: 3.7
Classifier: Programming Language :: Python :: 3.8
Classifier: Topic :: System :: Installation/Setup
Classifier: Topic :: System :: Systems Administration
Classifier: Topic :: Utilities
Requires-Python: >=3.7
Requires-Dist: crc32c
Requires-Dist: requests
